stonksfeed/__init__.py
stonksfeed/config.py
stonksfeed/measures.py
stonksfeed/models/article.py
stonksfeed/rss/__init__.py
stonksfeed/rss/base.py
stonksfeed/rss/rss_reader.py
stonksfeed/web/__init__.py
stonksfeed/web/siliconinvestor.py
stonksfeed-0.1.7.dist-info/LICENSE
stonksfeed-0.1.7.dist-info/METADATA
stonksfeed-0.1.7.dist-info/WHEEL
stonksfeed-0.1.7.dist-info/RECORD
