Metadata-Version: 2.1
Name: stonksfeed
Version: 0.1.7
Summary: A stock investor's news feed par excelance!
License: GPLv3
Author: m1yag1
Author-email: mike.arbelaez@gmail.com
Requires-Python: >=3.9,<4.0
Classifier: License :: Other/Proprietary License
Classifier: Programming Language :: Python :: 3
Classifier: Programming Language :: Python :: 3.9
Classifier: Programming Language :: Python :: 3.10
Classifier: Programming Language :: Python :: 3.11
Classifier: Programming Language :: Python :: 3.12
Requires-Dist: bs4 (>=0.0.1,<0.0.2)
Requires-Dist: jinja2 (>=3.1.2,<4.0.0)
Requires-Dist: python-dateutil (>=2.8.2,<3.0.0)
Requires-Dist: pytz (>=2023.3.post1,<2024.0)
Requires-Dist: requests (>=2.31.0,<3.0.0)
Requires-Dist: urllib3 (>=1.25.4,<1.27)
